stackoverflow_mcp/__init__.py
stackoverflow_mcp/__main__.py
stackoverflow_mcp/config.py
stackoverflow_mcp/logging.py
stackoverflow_mcp/main.py
stackoverflow_mcp/server.py
stackoverflow_mcp/stackoverflow_client.py
stackoverflow_fastmcp-0.2.6.dist-info/METADATA
stackoverflow_fastmcp-0.2.6.dist-info/WHEEL
stackoverflow_fastmcp-0.2.6.dist-info/entry_points.txt
stackoverflow_fastmcp-0.2.6.dist-info/licenses/LICENSE
stackoverflow_fastmcp-0.2.6.dist-info/RECORD
