Metadata-Version: 2.4
Name: stackoverflow-fastmcp
Version: 0.2.6
Summary: StackOverflow MCP server for querying programming Q&A using FastMCP framework
Project-URL: Homepage, https://github.com/NoTalkTech/stackoverflow-mcp
Project-URL: Documentation, https://github.com/NoTalkTech/stackoverflow-mcp#readme
Project-URL: Repository, https://github.com/NoTalkTech/stackoverflow-mcp.git
Project-URL: Bug Tracker, https://github.com/NoTalkTech/stackoverflow-mcp/issues
Project-URL: Changelog, https://github.com/NoTalkTech/stackoverflow-mcp/blob/main/CHANGELOG.md
Author-email: "biyu.huang" <h417652303@gmail.com>
Maintainer-email: "biyu.huang" <h417652303@gmail.com>
License: MIT
License-File: LICENSE
Keywords: api,cli,mcp,model-context-protocol,programming,qa,search,server,stackoverflow
Classifier: Development Status :: 4 - Beta
Classifier: Intended Audience :: Developers
Classifier: License :: OSI Approved :: MIT License
Classifier: Operating System :: OS Independent
Classifier: Programming Language :: Python :: 3
Classifier: Programming Language :: Python :: 3.12
Classifier: Programming Language :: Python :: 3.13
Classifier: Topic :: Internet :: WWW/HTTP :: HTTP Servers
Classifier: Topic :: Software Development :: Documentation
Classifier: Topic :: Software Development :: Libraries :: Python Modules
Classifier: Topic :: Text Processing :: Markup :: Markdown
Requires-Python: >=3.12
Requires-Dist: beautifulsoup4>=4.12.0
Requires-Dist: click>=8.0.0
Requires-Dist: fastmcp>=0.9.0
Requires-Dist: httpx>=0.25.0
Requires-Dist: markdownify>=0.11.0
Requires-Dist: pydantic>=2.0.0
Requires-Dist: python-dotenv>=1.0.0
Provides-Extra: dev
Requires-Dist: black>=23.0.0; extra == 'dev'
Requires-Dist: coverage>=7.0.0; extra == 'dev'
Requires-Dist: mypy>=1.0.0; extra == 'dev'
Requires-Dist: pytest-asyncio>=0.21.0; extra == 'dev'
Requires-Dist: pytest-httpx>=0.21.0; extra == 'dev'
Requires-Dist: pytest>=7.0.0; extra == 'dev'
Requires-Dist: ruff>=0.1.0; extra == 'dev'
Provides-Extra: test
Requires-Dist: coverage>=7.0.0; extra == 'test'
Requires-Dist: pytest-asyncio>=0.21.0; extra == 'test'
Requires-Dist: pytest-httpx>=0.21.0; extra == 'test'
Requires-Dist: pytest>=7.0.0; extra == 'test'
